wsql_sdk
