Metadata-Version: 1.1
Name: wsql-sdk
Version: 0.3.15
Summary: The chain of tools, that to make work with SQL easier
Home-page: https://github.com/WebSQL/sdk
Author: Bulat Gaifullin
Author-email: gaifullinbf@gmail.com
License: MIT
Platform: UNKNOWN
Classifier: Development Status :: 4 - Beta
Classifier: Environment :: Other Environment
Classifier: License :: OSI Approved :: MIT License
Classifier: Operating System :: MacOS :: MacOS X
Classifier: Operating System :: OS Independent
Classifier: Operating System :: POSIX
Classifier: Operating System :: POSIX :: Linux
Classifier: Operating System :: Unix
Classifier: Programming Language :: Python :: 3
Classifier: Programming Language :: Python :: 3.3
Classifier: Programming Language :: Python :: 3.4
Classifier: Topic :: Database
Classifier: Topic :: Database :: Database Engines/Servers
Requires: pyparsing
